semantra/__init__.py
semantra/models.py
semantra/pdf.py
semantra/semantra.py
semantra/util.py
semantra/client_public/favicon.png
semantra/client_public/global.css
semantra/client_public/index.html
semantra/client_public/build/bundle.css
semantra/client_public/build/bundle.js
semantra/client_public/build/bundle.js.map
semantra-0.1.12.dist-info/LICENSE
semantra-0.1.12.dist-info/METADATA
semantra-0.1.12.dist-info/WHEEL
semantra-0.1.12.dist-info/entry_points.txt
semantra-0.1.12.dist-info/top_level.txt
semantra-0.1.12.dist-info/RECORD
