Metadata-Version: 2.1
Name: semantra
Version: 0.1.12
Summary: A semantic search CLI tool
Author-email: Dylan Freedman <freedmand@gmail.com>
Project-URL: Bug Tracker, https://github.com/freedmand/semantra/issues
Project-URL: Homepage, https://github.com/freedmand/semantra
Project-URL: Repository, https://github.com/freedmand/semantra
Classifier: Programming Language :: Python :: 3
Classifier: License :: OSI Approved :: MIT License
Classifier: Operating System :: OS Independent
License-File: LICENSE
Requires-Dist: annoy-fixed>=1.16.3
Requires-Dist: click>=8.1.3
Requires-Dist: Flask>=2.2.3
Requires-Dist: openai>=0.27.2
Requires-Dist: Pillow>=9.5.0
Requires-Dist: pypdfium2>=4.5.0
Requires-Dist: python-dotenv>=1.0.0
Requires-Dist: numpy<2
Requires-Dist: tiktoken>=0.3.3
Requires-Dist: torch>=2.0.0
Requires-Dist: tqdm>=4.65.0
Requires-Dist: transformers>=4.27.4
Requires-Dist: setuptools
